{"docs":[{"Application":"SolidWorks Part","Author":"vdR Group","ComposedOf":["e906827e-eb0b-459e-870b-bee30f5be115"],"DateModified":"01/18/2016 13:41:54","FileExtension":"sldprt","FileName":"C:/Dev/lucidworks/Code/CADnection/data/Sample Files/SolidWorks/SWSampleAssy04/143-002.sldprt","Id":"1a803508-8af4-42f9-9b21-0c59244c2e0b","Name":"143-002","Size":"195 KB","StreamCache":"http://cadnection.vdr.com:8080/sc.jsp?sc=https://s3-us-west-1.amazonaws.com/cadnection.data/demo/1a803508-8af4-42f9-9b21-0c59244c2e0b.scs","Thumbnail":"https://s3-us-west-1.amazonaws.com/cadnection.data/demo/1a803508-8af4-42f9-9b21-0c59244c2e0b.png","Type":"Product Occurrence"},{"Application":"SolidWorks Part","Author":"vdR Group","DESCRIPTION":"143-002","FileExtension":"sldprt","FileName":"C:/Dev/lucidworks/Code/CADnection/data/Sample Files/SolidWorks/SWSampleAssy04/143-002.sldprt","Id":"e906827e-eb0b-459e-870b-bee30f5be115","MATERIAL":"TEST","Name":"Default","SW-Author(Author)":"joe","SW-Configuration Name(Configuration Name)":"Default","SW-Created Date(Created Date)":"Tuesday, November 5, 1996 8:34:52 AM","SW-File Name(File Name)":"143-002","SW-Folder Name(Folder Name)":"C:\\Junk\\SolidWorks\\SWSampleAssy04\\","SW-Last Saved By(Last Saved By)":"Craig.Dennis","SW-Last Saved Date(Last Saved Date)":"Monday, January 18, 2016 12:41:53 PM","SW-Long Date(Long Date)":"Monday, January 18, 2016","SW-Short Date(Short Date)":"1/18/2016","StreamCache":"http://cadnection.vdr.com:8080/sc.jsp?sc=https://s3-us-west-1.amazonaws.com/cadnection.data/demo/e906827e-eb0b-459e-870b-bee30f5be115.scs","Thumbnail":"https://s3-us-west-1.amazonaws.com/cadnection.data/demo/e906827e-eb0b-459e-870b-bee30f5be115.png","Type":"Product Occurrence","WhereUsed":"1a803508-8af4-42f9-9b21-0c59244c2e0b"}]}