{"docs":[{"Application":"SolidWorks Part","Author":"vdR Group","ComposedOf":["dbc4150c-4f67-4d28-909a-75d15286e970"],"DateModified":"01/18/2016 13:39:18","FileExtension":"sldprt","FileName":"C:/Dev/lucidworks/Code/CADnection/data/Sample Files/SolidWorks/SWSampleAssy03/pin.sldprt","Id":"acf131aa-b1d1-479a-b5e6-aaf7241aa422","Name":"pin","Size":"92 KB","StreamCache":"http://cadnection.vdr.com:8080/sc.jsp?sc=https://s3-us-west-1.amazonaws.com/cadnection.data/demo/acf131aa-b1d1-479a-b5e6-aaf7241aa422.scs","Thumbnail":"https://s3-us-west-1.amazonaws.com/cadnection.data/demo/acf131aa-b1d1-479a-b5e6-aaf7241aa422.png","Type":"Product Occurrence"},{"Application":"SolidWorks Part","Author":"vdR Group","FileExtension":"sldprt","FileName":"C:/Dev/lucidworks/Code/CADnection/data/Sample Files/SolidWorks/SWSampleAssy03/pin.sldprt","Id":"dbc4150c-4f67-4d28-909a-75d15286e970","Name":"Default","Project":"Oil Pump","Revision":"PRE-01","SW-Configuration Name(Configuration Name)":"Default","SW-Created Date(Created Date)":"Friday, May 17, 1996 3:49:31 PM","SW-File Name(File Name)":"pin","SW-Folder Name(Folder Name)":"C:\\Junk\\SolidWorks\\SWSampleAssy03\\","SW-Last Saved By(Last Saved By)":"Craig.Dennis","SW-Last Saved Date(Last Saved Date)":"Monday, January 18, 2016 12:39:16 PM","SW-Long Date(Long Date)":"Monday, January 18, 2016","SW-Short Date(Short Date)":"1/18/2016","StreamCache":"http://cadnection.vdr.com:8080/sc.jsp?sc=https://s3-us-west-1.amazonaws.com/cadnection.data/demo/dbc4150c-4f67-4d28-909a-75d15286e970.scs","Thumbnail":"https://s3-us-west-1.amazonaws.com/cadnection.data/demo/dbc4150c-4f67-4d28-909a-75d15286e970.png","Type":"Product Occurrence","WhereUsed":"acf131aa-b1d1-479a-b5e6-aaf7241aa422"}]}