{"docs":[{"Angle Display Precision":2,"Angle Units":15,"Application":"Inventor Part","Author":"vdR Group","Compacted":0,"Date Created":1069186804,"DateModified":"02/27/2006 23:32:18","Design Status":1,"Designer":"student","Document SubType Name":"Modeling","FileExtension":"ipt","FileName":"C:/Dev/lucidworks/Code/CADnection/data/Sample Files/Inventor/InvSample01/TABLE PLATE.ipt","Id":"37413752-4EB4E58E-DE69E7A3-A856CC49","Length Display Precision":3,"Length Units":8,"Mass Units":22,"Name":"TABLE PLATE.ipt","Part Number":"TABLE PLATE","Property Set Name":"Inventor Document Summary Information","Size":"215 KB","StreamCache":"http://cadnection.vdr.com:8080/sc.jsp?sc=https://s3-us-west-1.amazonaws.com/cadnection.data/demo/37413752-4EB4E58E-DE69E7A3-A856CC49.scs","Template":"\u0002","Thumbnail":"https://s3-us-west-1.amazonaws.com/cadnection.data/demo/37413752-4EB4E58E-DE69E7A3-A856CC49.png","Time Units":26,"Type":"Product Occurrence"}]}